dbconnector/__init__.py
dbconnector/connections.py
rahulmane_db_connector-0.1.0.dist-info/licenses/LICENSE
rahulmane_db_connector-0.1.0.dist-info/METADATA
rahulmane_db_connector-0.1.0.dist-info/WHEEL
rahulmane_db_connector-0.1.0.dist-info/top_level.txt
rahulmane_db_connector-0.1.0.dist-info/RECORD
