Metadata-Version: 2.4
Name: rahulmane-db-connector
Version: 0.1.0
Summary: A simple library to connect to MySQL, SQLite, and PostgreSQL.
Author-email: Rahul Mane <your.email@example.com>
License: 
Project-URL: Homepage, https://github.com/your-username/simple-db-connector
Project-URL: Bug Tracker, https://github.com/your-username/simple-db-connector/issues
Classifier: Programming Language :: Python :: 3
Classifier: License :: OSI Approved :: MIT License
Classifier: Operating System :: OS Independent
Classifier: Topic :: Database
Requires-Python: >=3.7
License-File: LICENSE
Requires-Dist: mysql-connector-python
Requires-Dist: psycopg2-binary
Dynamic: license-file
